belette/__init__.py
belette/belette.py
belette/licenses/0BSD.txt
belette/licenses/389-exception.txt
belette/licenses/AAL.txt
belette/licenses/ADSL.txt
belette/licenses/AFL-1.1.txt
belette/licenses/AFL-1.2.txt
belette/licenses/AFL-2.0.txt
belette/licenses/AFL-2.1.txt
belette/licenses/AFL-3.0.txt
belette/licenses/AGPL-1.0-only.txt
belette/licenses/AGPL-1.0-or-later.txt
belette/licenses/AGPL-3.0-only.txt
belette/licenses/AGPL-3.0-or-later.txt
belette/licenses/AMDPLPA.txt
belette/licenses/AML.txt
belette/licenses/AMPAS.txt
belette/licenses/ANTLR-PD-fallback.txt
belette/licenses/ANTLR-PD.txt
belette/licenses/APAFML.txt
belette/licenses/APL-1.0.txt
belette/licenses/APSL-1.0.txt
belette/licenses/APSL-1.1.txt
belette/licenses/APSL-1.2.txt
belette/licenses/APSL-2.0.txt
belette/licenses/Abstyles.txt
belette/licenses/Adobe-2006.txt
belette/licenses/Adobe-Glyph.txt
belette/licenses/Afmparse.txt
belette/licenses/Aladdin.txt
belette/licenses/Apache-1.0.txt
belette/licenses/Apache-1.1.txt
belette/licenses/Apache-2.0.txt
belette/licenses/Artistic-1.0-Perl.txt
belette/licenses/Artistic-1.0-cl8.txt
belette/licenses/Artistic-1.0.txt
belette/licenses/Artistic-2.0.txt
belette/licenses/Autoconf-exception-2.0.txt
belette/licenses/Autoconf-exception-3.0.txt
belette/licenses/BSD-1-Clause.txt
belette/licenses/BSD-2-Clause-Patent.txt
belette/licenses/BSD-2-Clause-Views.txt
belette/licenses/BSD-2-Clause.txt
belette/licenses/BSD-3-Clause-Attribution.txt
belette/licenses/BSD-3-Clause-Clear.txt
belette/licenses/BSD-3-Clause-LBNL.txt
belette/licenses/BSD-3-Clause-Modification.txt
belette/licenses/BSD-3-Clause-No-Military-License.txt
belette/licenses/BSD-3-Clause-No-Nuclear-License-2014.txt
belette/licenses/BSD-3-Clause-No-Nuclear-License.txt
belette/licenses/BSD-3-Clause-No-Nuclear-Warranty.txt
belette/licenses/BSD-3-Clause-Open-MPI.txt
belette/licenses/BSD-3-Clause.txt
belette/licenses/BSD-4-Clause-Shortened.txt
belette/licenses/BSD-4-Clause-UC.txt
belette/licenses/BSD-4-Clause.txt
belette-0.1.0.dist-info/entry_points.txt
belette-0.1.0.dist-info/WHEEL
belette-0.1.0.dist-info/METADATA
belette-0.1.0.dist-info/RECORD
